ida_pro_mcp/__init__.py
ida_pro_mcp/__main__.py
ida_pro_mcp/ida_mcp.py
ida_pro_mcp/idalib_server.py
ida_pro_mcp/server.py
ida_pro_mcp/ida_mcp/__init__.py
ida_pro_mcp/ida_mcp/api_analysis.py
ida_pro_mcp/ida_mcp/api_core.py
ida_pro_mcp/ida_mcp/api_debug.py
ida_pro_mcp/ida_mcp/api_memory.py
ida_pro_mcp/ida_mcp/api_modify.py
ida_pro_mcp/ida_mcp/api_python.py
ida_pro_mcp/ida_mcp/api_resources.py
ida_pro_mcp/ida_mcp/api_stack.py
ida_pro_mcp/ida_mcp/api_types.py
ida_pro_mcp/ida_mcp/http.py
ida_pro_mcp/ida_mcp/rpc.py
ida_pro_mcp/ida_mcp/sync.py
ida_pro_mcp/ida_mcp/utils.py
ida_pro_mcp/ida_mcp/zeromcp/__init__.py
ida_pro_mcp/ida_mcp/zeromcp/jsonrpc.py
ida_pro_mcp/ida_mcp/zeromcp/mcp.py
iflow_mcp_ida_pro_mcp-2.0.0.dist-info/licenses/LICENSE
iflow_mcp_ida_pro_mcp-2.0.0.dist-info/METADATA
iflow_mcp_ida_pro_mcp-2.0.0.dist-info/WHEEL
iflow_mcp_ida_pro_mcp-2.0.0.dist-info/entry_points.txt
iflow_mcp_ida_pro_mcp-2.0.0.dist-info/top_level.txt
iflow_mcp_ida_pro_mcp-2.0.0.dist-info/RECORD
