Metadata-Version: 2.4
Name: iflow-mcp_ida-pro-mcp
Version: 2.0.0
Summary: Vibe reversing with IDA Pro
Author: mrexodia, can1357, IDA Pro MCP Contributors
Project-URL: Repository, https://github.com/mrexodia/ida-pro-mcp
Project-URL: Issues, https://github.com/mrexodia/ida-pro-mcp/issues
Keywords: ida,mcp,llm,plugin
Classifier: Development Status :: 5 - Production/Stable
Classifier: Intended Audience :: Developers
Classifier: Programming Language :: Python :: 3
Classifier: Programming Language :: Python :: 3.11
Classifier: Operating System :: MacOS
Classifier: Operating System :: Microsoft :: Windows
Requires-Python: >=3.11
License-File: LICENSE
Requires-Dist: idapro>=0.0.7
Requires-Dist: tomli-w>=1.0.0
Dynamic: license-file
